alanbootstrap/__init__.py
alanbootstrap/components/__init__.py
alanbootstrap/components/ast.py
alanbootstrap/models/__init__.py
alanbootstrap/models/ast.py
alanbootstrap/models/decoders.py
alanbootstrap/models/encoder.py
alanbootstrap/models/functions.py
alanbootstrap/models/layers.py
alanbootstrap/utils/__init__.py
alanbootstrap/utils/constants.py
alanbootstrap/utils/path_resolver.py
bin/__init__.py
bin/ast_al_bin.py
alanbootstrap-0.2.0.dist-info/METADATA
alanbootstrap-0.2.0.dist-info/WHEEL
alanbootstrap-0.2.0.dist-info/top_level.txt
alanbootstrap-0.2.0.dist-info/RECORD
