Metadata-Version: 2.1
Name: alanbootstrap
Version: 0.2.0
Summary: Boostrap Module for Alan
Home-page: https://bitbucket.org/rbcmllab/data_bootstrap/alanbootstrap/master
Author: Keyi Tang
Author-email: keyi.tang@rbc.com
License: UNKNOWN
Platform: UNKNOWN
Classifier: Programming Language :: Python :: 3
Classifier: License :: OSI Approved :: MIT License
Classifier: Operating System :: OS Independent
